bing_translator/__init__.py
bing_translator/__main__.py
bing_translator/core.py
bing_terminal_translator-1.0.6.dist-info/LICENSE
bing_terminal_translator-1.0.6.dist-info/METADATA
bing_terminal_translator-1.0.6.dist-info/WHEEL
bing_terminal_translator-1.0.6.dist-info/entry_points.txt
bing_terminal_translator-1.0.6.dist-info/top_level.txt
bing_terminal_translator-1.0.6.dist-info/RECORD
