Metadata-Version: 2.1
Name: bing-terminal-translator
Version: 1.0.6
Summary: The project is designed as a quick translation tool built into the terminal
Home-page: UNKNOWN
Author: 87Keys
Author-email: meme_me2019@outlook.com
License: UNKNOWN
Platform: UNKNOWN
Classifier: Programming Language :: Python
Classifier: Programming Language :: Python :: 3
Classifier: Programming Language :: Python :: 3 :: Only
Classifier: Programming Language :: Python :: 3.6
Classifier: Programming Language :: Python :: 3.7
Classifier: Programming Language :: Python :: 3.8
Classifier: Programming Language :: Python :: 3.9
Classifier: Topic :: Software Development :: Libraries :: Python Modules
Requires-Python: >=3.6
License-File: LICENSE
Requires-Dist: bing-translation-for-python (<3.0.0)
Requires-Dist: pyperclip
